visionlib/__init__.py
visionlib/face/__init__.py
visionlib/face/detection.py
visionlib/face/dnn_detector.py
visionlib/face/haar_detector.py
visionlib/face/hog_detector.py
visionlib/face/mtcnn_detector.py
visionlib/gender/__init__.py
visionlib/gender/detection.py
visionlib/keypoints/__init__.py
visionlib/keypoints/detection.py
visionlib/keypoints/dlib_detector.py
visionlib/keypoints/mtcnn_detector.py
visionlib/models/deploy.prototxt
visionlib/models/res10_300x300_ssd_iter_140000.caffemodel
visionlib/object/__init__.py
visionlib/object/classifier/__init__.py
visionlib/object/classifier/detection.py
visionlib/object/classifier/inception_detector.py
visionlib/object/classifier/vgg_detector.py
visionlib/object/classifier/xception_detector.py
visionlib/object/detection/__init__.py
visionlib/object/detection/detection.py
visionlib/utils/__init__.py
visionlib/utils/imgutils.py
visionlib/utils/urls.json
visionlib/utils/webutils.py
visionlib-1.4.5.dist-info/LICENSE
visionlib-1.4.5.dist-info/METADATA
visionlib-1.4.5.dist-info/WHEEL
visionlib-1.4.5.dist-info/top_level.txt
visionlib-1.4.5.dist-info/RECORD
