Metadata-Version: 2.1
Name: visionlib
Version: 1.4.5
Summary: A simple, easy to use and customizeble cv library 
Home-page: https://github.com/ashwinvin/Visionlib
Author: Ashwin Vinod
Author-email: ashwinvinodsa@gmail.com
License: UNKNOWN
Download-URL: https://github.com/ashwinvin/Visionlib/archive/v1.4.5.tar.gz
Keywords: Deep learning,Vision,cv
Platform: UNKNOWN
Classifier: Programming Language :: Python :: 3
Classifier: License :: OSI Approved :: MIT License
Classifier: Operating System :: OS Independent
Requires-Python: >=3.6
Requires-Dist: mtcnn
Requires-Dist: opencv-python
Requires-Dist: dlib
Requires-Dist: wget
Requires-Dist: numpy
Requires-Dist: pafy
Requires-Dist: youtube-dl
